LICENSE.rst
MANIFEST.in
Makefile
README.rst
setup.py
test_makestatic.py
Flask_MakeStatic.egg-info/PKG-INFO
Flask_MakeStatic.egg-info/SOURCES.txt
Flask_MakeStatic.egg-info/dependency_links.txt
Flask_MakeStatic.egg-info/not-zip-safe
Flask_MakeStatic.egg-info/requires.txt
Flask_MakeStatic.egg-info/top_level.txt
docs/Makefile
docs/conf.py
docs/index.rst
docs/make.bat
docs/_static/custom.css
docs/_themes/.git
docs/_themes/.gitignore
docs/_themes/LICENSE
docs/_themes/README
docs/_themes/flask_theme_support.py
docs/_themes/flask_theme_support.pyc
docs/_themes/flask/layout.html
docs/_themes/flask/relations.html
docs/_themes/flask/theme.conf
docs/_themes/flask/static/flasky.css_t
docs/_themes/flask/static/small_flask.css
docs/_themes/flask_small/layout.html
docs/_themes/flask_small/theme.conf
docs/_themes/flask_small/static/flasky.css_t
flask_makestatic/__init__.py
flask_makestatic/_compat.py
flask_makestatic/watcher.py