Metadata-Version: 1.1
Name: Flask-MakeStatic
Version: 0.3.0
Summary: Make for your flask app assets
Home-page: https://github.com/DasIch/Flask-MakeStatic
Author: Daniel Neuhäuser
Author-email: ich@danielneuhaeuser.de
License: BSD
Platform: any
Classifier: Environment :: Web Environment
Classifier: Intended Audience :: Developers
Classifier: License :: OSI Approved :: BSD License
Classifier: Operating System :: OS Independent
Classifier: Programming Language :: Python
Classifier: Programming Language :: Python :: 2
Classifier: Programming Language :: Python :: 2.6
Classifier: Programming Language :: Python :: 2.7
Classifier: Programming Language :: Python :: 3
Classifier: Programming Language :: Python :: 3.3
Classifier: Topic :: Internet :: WWW/HTTP :: Dynamic Content
Classifier: Topic :: Software Development :: Libraries :: Python Modules
